{"stats":{"minecraft:killed":{"minecraft:cave_spider":2,"minecraft:spider":1,"minecraft:skeleton":11,"minecraft:bee":1,"minecraft:silverfish":5,"minecraft:piglin_brute":1,"minecraft:skeleton_horse":1,"minecraft:pillager":4,"enemyexpansion:meature":1,"minecraft:zombie":13,"undead_unleashed:shadewraith":2,"minecraft:mooshroom":1,"minecraft:stray":14,"undead_unleashed:haunter":1,"whisperwoods:moth":1,"enemyexpansion:direwolf":2,"enemyexpansion:faller":1,"minecraft:drowned":1,"goblintraders:goblin_trader":1,"enemyexpansion:sprinter":1,"royalvariations:royal_zombie":2,"sons_of_sins:betrayed_guzzler":1,"minecraft:villager":3},"minecraft:custom":{"enigmaticlegacy:play_time_with_seven_curses":0,"lootr:looted_stat":125,"minecraft:interact_with_crafting_table":27,"minecraft:leave_game":12,"minecraft:time_since_death":11838,"minecraft:damage_resisted":0,"minecraft:sprint_one_cm":412944,"minecraft:damage_blocked_by_shield":2715,"minecraft:drop":184,"minecraft:talked_to_villager":10,"minecraft:play_time":288053,"minecraft:deaths":55,"minecraft:jump":2850,"minecraft:walk_on_water_one_cm":26522,"minecraft:interact_with_furnace":17,"minecraft:interact_with_loom":2,"minecraft:sleep_in_bed":2,"minecraft:waystone_activated":6,"minecraft:damage_dealt":34616,"minecraft:crouch_one_cm":8517,"minecraft:interact_with_smoker":1,"minecraft:inspect_dispenser":1,"minecraft:mob_kills":72,"minecraft:damage_dealt_resisted":1311,"minecraft:climb_one_cm":16475,"minecraft:walk_one_cm":1078313,"minecraft:sneak_time":2449,"minecraft:walk_under_water_one_cm":255800,"minecraft:boat_one_cm":582,"minecraft:total_world_time":288053,"enigmaticlegacy:play_time_without_seven_curses":297830,"minecraft:time_since_rest":11863,"minecraft:damage_taken":21746,"minecraft:fly_one_cm":597360,"minecraft:open_chest":43,"minecraft:aviate_one_cm":3987022,"minecraft:fall_one_cm":118190},"minecraft:dropped":{"byg:biomepedia":2,"minecraft:iron_sword":2,"cisco_mod:adventurer_helmet":1,"knightlib:small_essence":3,"minecraft:dark_oak_stairs":1,"minecraft:porkchop":1,"minecolonies:scroll_buff":48,"ecologics:coconut_slice":4,"cisco_mod:adventurer_leggings":4,"undead_unleashed:grave_metal_scrap":2,"minecraft:item_frame":6,"minecraft:cobblestone_stairs":2,"minecraft:cornflower":1,"forbidden_arcanus:darkstone":12,"twigs:twig":41,"minecraft:armor_stand":1,"minecraft:bone":4,"majruszsdifficulty:tattered_chestplate":1,"minecraft:sugar_cane":1,"minecraft:cobbled_deepslate":8,"alexsmobs:animal_dictionary":1,"twigs:schist":4,"aether:golden_gloves":1,"minecraft:birch_sapling":14,"minecraft:obsidian":2,"minecraft:rotten_flesh":22,"minecraft:prismarine":1,"patchouli:guide_book":3,"iter_rpg:abyssquartz_shard":1,"minecraft:leather_chestplate":2,"iter_rpg:frosty_grass":1,"iter_rpg:polished_grimstone":5,"minecraft:tipped_arrow":1,"minecraft:gunpowder":64,"apotheosis:gem":16,"minecraft:stone_brick_wall":6,"minecraft:leather_boots":3,"minecraft:spruce_slab":4,"minecraft:arrow":2,"minecraft:prismarine_bricks":1,"minecraft:netherrack":68,"minecraft:golden_helmet":1,"minecraft:cobblestone":2,"minecraft:prismarine_crystals":2,"minecraft:book":1,"minecraft:granite":12,"minecraft:spruce_stairs":2,"minecraft:coal":2,"minecraft:stick":22,"iter_rpg:grimstone_bricks":6,"ars_nouveau:worn_notebook":1,"galosphere:raw_silver":2,"minecraft:diorite":6,"byg:soapstone":6,"minecraft:wooden_axe":1,"minecraft:rose_bush":1,"minecraft:smooth_quartz":3,"forbidden_arcanus:spawner_scrap":7,"minecraft:iron_leggings":1,"minecraft:white_banner":1,"minecraft:chainmail_leggings":2,"irons_spellbooks:frozen_bone":6,"enigmaticlegacy:withered_tome":2,"twigs:rhyolite":5,"minecraft:kelp":3,"cisco_mod:adventurer_boots":2,"minecraft:cobblestone_wall":18,"twigs:roseate_seashell":1,"minecraft:bowl":13,"minecraft:tuff":3,"minecraft:white_carpet":2,"byg:tall_allium":1,"minecraft:iron_boots":1,"minecraft:flint_and_steel":1,"minecraft:lily_of_the_valley":2,"minecraft:sea_pickle":1,"minecraft:spruce_planks":4,"minecraft:iron_chestplate":1,"minecraft:mossy_stone_bricks":7,"minecraft:yellow_bed":1,"minecraft:spider_eye":2,"minecraft:stone_bricks":2,"minecraft:bow":2,"minecraft:stone_pickaxe":1,"minecraft:wooden_pickaxe":1,"ecologics:seashell":1,"byg:magmatic_stone":6,"minecraft:dark_prismarine":2,"immersive_armors:wooden_helmet":1},"minecraft:crafted":{"minecraft:birch_planks":88,"cisco_mod:brightsteel_ingot":24,"minecraft:paper":9,"sophisticatedbackpacks:diamond_backpack":1,"minecraft:iron_block":12,"minecraft:netherite_scrap":2,"sophisticatedbackpacks:gold_backpack":1,"minecraft:air":0,"minecraft:firework_rocket":27},"minecraft:mined":{"minecraft:dark_oak_planks":1,"minecraft:spruce_planks":6,"minecraft:cobblestone_stairs":1,"minecraft:sculk_vein":8,"minecraft:granite":12,"minecraft:spawner":1,"minecraft:tall_seagrass":1,"minecraft:magma_block":1,"minecraft:glowstone":48,"minecraft:fire":5,"minecraft:dark_oak_stairs":1,"darkerdepths:shale":2,"minecraft:soul_wall_torch":1,"byg:scorched_grass":1,"minecraft:red_bed":1,"minecraft:kelp_plant":2,"minecraft:soul_fire":5,"minecraft:torch":1,"undead_unleashed:grave_soil":2,"minecraft:melon":4,"galosphere:silver_ore":2,"minecraft:nether_quartz_ore":14,"minecraft:cobblestone":20,"minecraft:sugar_cane":12,"minecraft:cyan_bed":2,"minecraft:grindstone":1,"minecraft:prismarine":1,"minecraft:oak_planks":4,"byg:magmatic_stone":9,"minecraft:seagrass":2,"byg:soapstone":6,"lootr:trophy":1,"forbidden_arcanus:darkstone":13,"ecologics:seashell":1,"ars_nouveau:archwood_planks":2,"minecraft:birch_log":44,"minecraft:tnt":9,"twigs:schist":4,"minecraft:smooth_quartz":4,"minecraft:sand":1,"structure_gel:dynamic_spawner":2,"twigs:rhyolite":5,"ars_nouveau:red_archwood_wood":1,"minecraft:netherrack":168,"minecraft:oak_leaves":1,"minecraft:deepslate":64,"minecraft:dark_prismarine":2,"minecraft:tuff":4,"minecraft:mossy_cobblestone":2,"minecraft:sea_lantern":1,"minecraft:dark_oak_fence":2,"minecraft:spruce_fence":2,"minecraft:kelp":1,"minecraft:hay_block":11,"forbidden_arcanus:deepslate_arcane_crystal_ore":1,"minecraft:andesite":1,"twigs:bronzed_seashell":1,"minecraft:gold_block":2,"minecraft:bookshelf":15,"minecraft:lantern":1,"minecraft:stone":51,"minecraft:white_wool":6,"atmospheric:aspen_log":1,"minecraft:crafting_table":5,"twigs:roseate_seashell":1,"minecraft:rose_bush":1,"iter_rpg:frosty_grass":1,"minecraft:sculk":15,"minecraft:diorite":6,"minecraft:prismarine_bricks":1,"supplementaries:urn":1,"minecraft:birch_planks":2,"forbidden_arcanus:xpetrified_ore":7,"iter_rpg:abyss_quartz":1,"minecraft:birch_leaves":2,"minecraft:yellow_bed":1,"minecraft:coal_ore":30,"minecraft:cobweb":8,"minecraft:cracked_stone_bricks":9,"minecraft:stone_bricks":9,"byg:tall_allium":1,"minecraft:mossy_stone_bricks":19},"minecraft:used":{"minecraft:shield":31,"minecraft:iron_sword":317,"lootr:trophy":1,"undead_unleashed:grave_metal_axe":57,"minecraft:lava_bucket":11,"minecraft:lantern":3,"minecraft:birch_sapling":6,"atmospheric:aspen_sapling":1,"simplyswords:iron_longsword":7,"minecraft:stone_bricks":3,"immersive_armors:wooden_chestplate":1,"minecraft:bow":21,"minecraft:hay_block":3,"minecraft:furnace":2,"immersive_armors:wooden_helmet":1,"minecraft:mossy_stone_bricks":12,"minecraft:stone_pickaxe":75,"minecraft:oak_planks":2,"minecraft:wooden_pickaxe":8,"minecraft:white_wool":22,"ars_nouveau:archwood_planks":6,"waystones:waystone":1,"farmersdelight:ratatouille":16,"minecraft:firework_rocket":82,"byg:magmatic_stone":2,"minecraft:cyan_bed":2,"minecraft:wooden_sword":7,"minecraft:cooked_rabbit":6,"minecraft:andesite":1,"cisco_mod:brightsteel_chestplate":1,"minecraft:enchanting_table":1,"waystones:sandy_waystone":1,"minecraft:flint_and_steel":1,"minecraft:dried_kelp":4,"minecraft:spruce_planks":3,"minecraft:netherrack":39,"minecraft:torch":65,"minecraft:dirt":8,"minecraft:dark_oak_planks":1,"minecraft:wooden_axe":41,"minecraft:bookshelf":10,"minecraft:smooth_quartz":1,"minecraft:cobbled_deepslate":9,"minecraft:water_bucket":7,"minecraft:birch_planks":91,"minecraft:birch_boat":1,"minecraft:cracked_stone_bricks":8,"minecraft:mossy_cobblestone":2,"minecraft:crafting_table":11,"minecraft:painting":2,"farmersdelight:bacon_and_eggs":9,"cisco_mod:adventurer_helmet":1,"darkerdepths:shale":2,"waystones:mossy_waystone":1,"minecraft:iron_pickaxe":479,"minecraft:spruce_pressure_plate":1,"immersive_armors:wooden_boots":1,"twigs:bronzed_seashell":1,"minecraft:cobblestone":75,"minecraft:bucket":20,"minecraft:yellow_bed":1,"alexsmobs:animal_dictionary":1,"immersive_armors:wooden_leggings":1},"minecraft:picked_up":{"twigs:roseate_seashell":1,"atmospheric:aspen_sapling":1,"forbidden_arcanus:xpetrified_orb":7,"minecraft:string":10,"darkerdepths:shale":2,"minecraft:armor_stand":1,"atmospheric:aspen_log":1,"minecraft:sea_pickle":1,"minecraft:cobbled_deepslate":64,"minecraft:spruce_planks":7,"minecraft:rose_bush":1,"minecraft:smooth_quartz":4,"minecraft:melon_slice":22,"minecraft:golden_helmet":1,"minecraft:tipped_arrow":6,"minecraft:spruce_pressure_plate":1,"minecraft:stick":23,"apotheosis:gem":17,"minecraft:torch":1,"minecraft:spruce_stairs":2,"minecraft:porkchop":1,"minecraft:diorite":6,"minecraft:rotten_flesh":24,"cisco_mod:adventurer_leggings":2,"ars_nouveau:worn_notebook":1,"ars_nouveau:red_archwood_wood":1,"supplementaries:ash":15,"minecraft:cobblestone":73,"minecraft:birch_log":42,"majruszsaccessories:tool_scraps":1,"minecraft:leather_chestplate":2,"minecraft:andesite":1,"minecraft:tuff":3,"minecraft:prismarine_bricks":1,"minecraft:wither_skeleton_skull":1,"lootr:trophy":1,"minecraft:dirt":19,"minecraft:lantern":3,"minecraft:leather_boots":3,"minecraft:bone":30,"minecraft:bow":3,"minecraft:grindstone":1,"twigs:schist":4,"minecraft:mossy_stone_bricks":19,"minecraft:glowstone_dust":139,"galosphere:raw_silver":2,"twigs:twig":41,"minecraft:prismarine":1,"minecraft:oak_planks":2,"irons_spellbooks:frozen_bone":34,"minecraft:lily_of_the_valley":2,"minecraft:cyan_bed":2,"byg:magmatic_stone":8,"minecraft:mossy_cobblestone":2,"minecraft:dark_prismarine":2,"waystones:waystone":1,"iter_rpg:abyssquartz_shard":1,"minecraft:granite":12,"minecraft:emerald":4,"twigs:rhyolite":5,"minecraft:netherrack":162,"iter_rpg:spawner_fragment":2,"minecraft:crafting_table":6,"byg:soapstone":6,"minecolonies:scroll_buff":32,"minecraft:brown_mushroom":64,"ecologics:seashell":1,"minecraft:stone_brick_wall":6,"minecraft:gold_block":2,"ars_nouveau:archwood_planks":2,"minecraft:cornflower":1,"minecraft:red_bed":1,"minecraft:netherite_scrap":1,"minecraft:white_carpet":2,"minecraft:item_frame":6,"minecraft:cracked_stone_bricks":8,"minecraft:beef":3,"minecraft:spruce_slab":4,"minecraft:sugar_cane":33,"minecraft:birch_sapling":21,"knightlib:small_essence":4,"ecologics:coconut_slice":4,"minecraft:bowl":2,"minecraft:spruce_fence":1,"minecraft:prismarine_crystals":2,"minecraft:dark_oak_planks":1,"minecraft:tnt":4,"byg:biomepedia":1,"minecraft:arrow":31,"minecraft:hay_block":11,"minecraft:saddle":2,"minecraft:gold_ingot":3,"minecraft:mutton":4,"forbidden_arcanus:spawner_scrap":10,"minecraft:white_wool":6,"minecraft:air":0,"minecraft:leather":7,"minecraft:birch_planks":2,"minecraft:gunpowder":64,"minecraft:yellow_bed":2,"minecraft:cobblestone_wall":18,"minecraft:cobblestone_stairs":2,"minecraft:white_banner":1,"minecraft:apple":1,"minecraft:stone_bricks":5,"minecraft:kelp":3,"minecraft:stone_pickaxe":2,"minecraft:iron_sword":1,"forbidden_arcanus:darkstone":12,"minecraft:dark_oak_stairs":1,"minecraft:book":49,"minecraft:quartz":14,"iter_rpg:frosty_grass":1,"twigs:bronzed_seashell":1,"undead_unleashed:grave_metal_scrap":17,"minecraft:spider_eye":2,"byg:tall_allium":1,"minecraft:chainmail_leggings":2,"minecraft:painting":2,"undead_unleashed:grave_metal_axe":1,"minecraft:coal":30},"minecraft:broken":{"minecraft:iron_chestplate":1,"alexsmobs:rocky_chestplate":1,"minecraft:iron_sword":1,"cisco_mod:adventurer_helmet":1,"minecraft:shield":1,"minecraft:iron_pickaxe":1},"minecraft:killed_by":{"minecraft:piglin_brute":3,"iter_rpg:mournstone":1,"minecraft:pillager":2,"undead_unleashed:shadewraith":1,"minecraft:drowned":2,"undead_unleashed:frenzied_knight":1,"sons_of_sins:betrayed_guzzler":1,"minecraft:vindicator":2,"minecraft:silverfish":1,"minecraft:cave_spider":1,"minecraft:zombie":3,"enemyexpansion:invisicreeper":1,"minecraft:vex":1,"alexsmobs:skelewag":1,"minecraft:player":1,"minecraft:stray":3,"minecraft:enderman":2,"mutantmonsters:mutant_skeleton":7,"minecraft:skeleton":13}},"DataVersion":3120}